time_daily_report/__init__.py
time_daily_report/daily.py
time_daily_report/file_parsers.py
time_daily_report/utils.py
time_daily_report/validation_key_ans.json
mhealth_time_daily_report-1.2.2.dist-info/LICENSE
mhealth_time_daily_report-1.2.2.dist-info/METADATA
mhealth_time_daily_report-1.2.2.dist-info/WHEEL
mhealth_time_daily_report-1.2.2.dist-info/top_level.txt
mhealth_time_daily_report-1.2.2.dist-info/RECORD
