Metadata-Version: 2.1
Name: mhealth-time-daily-report
Version: 1.2.2
Summary: Package to generate daily reports for TIME study data
Home-page: https://bitbucket.org/mhealthresearchgroup/daily_report_cluster/src/master/
Author: Aditya Ponnada
Author-email: ponnada.a@northeastern.edu
Classifier: Programming Language :: Python :: 3
Classifier: License :: OSI Approved :: MIT License
Classifier: Operating System :: OS Independent
Requires-Python: >=3.6
License-File: LICENSE
